{"activityId": 11972000419, "activityName": "Pflugerville Future", "startTimeLocal": "2023-09-07 17:15:21", "startTimeGMT": "2023-09-07 22:15:21", "activityType": {"typeId": 4, "typeKey": "other", "parentTypeId": 17, "isHidden": false, "trimmable": true, "restricted": false}, "eventType": {"typeId": 9, "typeKey": "uncategorized", "sortOrder": 10}, "distance": 62.41999816894531, "duration": 2730.6669921875, "elapsedDuration": 2730.6669921875, "movingDuration": 23.0, "averageSpeed": 0.023000000044703484, "maxSpeed": 1.2130000591278076, "startLatitude": 30.447312220931053, "startLongitude": -97.64956338331103, "hasPolyline": true, "hasImages": false, "ownerId": 104355181, "ownerDisplayName": "4f38881e-d967-46da-bb7b-6d423fe5470d", "ownerFullName": "Dhinesh", "ownerProfileImageUrlSmall": "https://s3.amazonaws.com/garmin-connect-prod/profile_images/13af3aa6-824b-4db4-8d04-74c652855cde-104355181.png", "ownerProfileImageUrlMedium": "https://s3.amazonaws.com/garmin-connect-prod/profile_images/1b9a9653-c6bb-42f9-8b18-5aa78975da3a-104355181.png", "ownerProfileImageUrlLarge": "https://s3.amazonaws.com/garmin-connect-prod/profile_images/fe3cf31e-c58e-4bd8-83f8-42b825174ca3-104355181.png", "calories": 403.0, "bmrCalories": 67.0, "averageHR": 137.0, "maxHR": 183.0, "averageRunningCadenceInStepsPerMinute": 37.171875, "maxRunningCadenceInStepsPerMinute": 159.0, "steps": 2004, "userRoles": ["SCOPE_GOLF_API_READ", "SCOPE_ATP_READ", "SCOPE_DIVE_API_WRITE", "SCOPE_COMMUNITY_COURSE_ADMIN_READ", "SCOPE_DIVE_API_READ", "SCOPE_DI_OAUTH_2_CLIENT_READ", "SCOPE_CONNECT_WRITE", "SCOPE_COMMUNITY_COURSE_WRITE", "SCOPE_MESSAGE_GENERATION_READ", "SCOPE_DI_OAUTH_2_CLIENT_REVOCATION_ADMIN", "SCOPE_CONNECT_WEB_TEMPLATE_RENDER", "SCOPE_OMT_SUBSCRIPTION_ADMIN_READ", "SCOPE_CONNECT_NON_SOCIAL_SHARED_READ", "SCOPE_CONNECT_READ", "SCOPE_DI_OAUTH_2_TOKEN_ADMIN", "ROLE_CONNECTUSER", "ROLE_FITNESS_USER", "ROLE_WELLNESS_USER", "ROLE_OUTDOOR_USER", "ROLE_GHS_USER"], "privacy": {"typeId": 2, "typeKey": "private"}, "userPro": false, "hasVideo": false, "timeZoneId": 152, "beginTimestamp": 1694124921000, "sportTypeId": 255, "aerobicTrainingEffect": 4.0, "anaerobicTrainingEffect": 2.0, "avgStrideLength": 3.689706261501176, "deviceId": 3383025111, "minElevation": 244.72283935546875, "maxElevation": 247.20834350585938, "maxDoubleCadence": 159.0, "summarizedDiveInfo": {"summarizedDiveGases": []}, "maxVerticalSpeed": 0.007239205496651787, "manufacturer": "GARMIN", "locationName": "Pflugerville", "lapCount": 1, "endLatitude": 30.447342563420534, "endLongitude": -97.64918795786798, "waterEstimated": 272.0, "minActivityLapDuration": 2730.6669921875, "aerobicTrainingEffectMessage": "HIGHLY_IMPROVING_AEROBIC_FITNESS_3", "anaerobicTrainingEffectMessage": "MAINTAINING_ANAEROBIC_BASE_1", "splitSummaries": [], "hasSplits": false, "moderateIntensityMinutes": 25, "vigorousIntensityMinutes": 18, "purposeful": false, "manualActivity": false, "pr": false, "autoCalcCalories": false, "elevationCorrected": true, "atpActivity": false, "favorite": false, "decoDive": false, "parent": false}