{"activityId": 9048501644, "activityUUID": {"uuid": "80858e93-e4b1-47f2-a8cf-bd941e2ada5c"}, "activityName": "Treadmill Running", "userProfileId": 104355181, "isMultiSportParent": false, "activityTypeDTO": {"typeId": 18, "typeKey": "treadmill_running", "parentTypeId": 1, "isHidden": false, "restricted": false, "trimmable": true}, "eventTypeDTO": {"typeId": 9, "typeKey": "uncategorized", "sortOrder": 10}, "accessControlRuleDTO": {"typeId": 1, "typeKey": "public"}, "timeZoneUnitDTO": {"unitId": 152, "unitKey": "America/Chicago", "factor": 0.0, "timeZone": "America/Chicago"}, "metadataDTO": {"isOriginal": true, "deviceApplicationInstallationId": 902934, "agentApplicationInstallationId": null, "agentString": null, "fileFormat": {"formatId": 7, "formatKey": "fit"}, "associatedCourseId": null, "lastUpdateDate": "2022-06-22T20:59:16.0", "uploadedDate": "2022-06-19T18:45:24.0", "videoUrl": null, "hasPolyline": false, "hasChartData": true, "hasHrTimeInZones": true, "hasPowerTimeInZones": false, "userInfoDto": {"userProfilePk": 104355181, "displayname": "4f38881e-d967-46da-bb7b-6d423fe5470d", "fullname": "Dhinesh", "profileImageUrlLarge": "https://s3.amazonaws.com/garmin-connect-prod/profile_images/fe3cf31e-c58e-4bd8-83f8-42b825174ca3-104355181.png", "profileImageUrlMedium": "https://s3.amazonaws.com/garmin-connect-prod/profile_images/1b9a9653-c6bb-42f9-8b18-5aa78975da3a-104355181.png", "profileImageUrlSmall": "https://s3.amazonaws.com/garmin-connect-prod/profile_images/13af3aa6-824b-4db4-8d04-74c652855cde-104355181.png", "userPro": false}, "childIds": [], "childActivityTypes": [], "sensors": [], "activityImages": [], "manufacturer": "GARMIN", "diveNumber": null, "lapCount": 4, "associatedWorkoutId": null, "isAtpActivity": null, "deviceMetaDataDTO": {"deviceId": "3383025111", "deviceTypePk": 35576, "deviceVersionPk": 902934}, "hasIntensityIntervals": false, "hasSplits": true, "eBikeMaxAssistModes": null, "eBikeBatteryUsage": null, "eBikeBatteryRemaining": null, "eBikeAssistModeInfoDTOList": null, "hasRunPowerWindData": null, "calendarEventInfo": null, "groupRideUUID": null, "hasHeatMap": false, "personalRecord": false, "autoCalcCalories": false, "favorite": false, "manualActivity": false, "runPowerWindDataEnabled": null, "trimmed": false, "gcj02": false, "elevationCorrected": false}, "summaryDTO": {"startTimeLocal": "2022-06-19T13:02:11.0", "startTimeGMT": "2022-06-19T18:02:11.0", "distance": 5830.09, "duration": 2499.678, "movingDuration": 2455.0, "elapsedDuration": 2499.678, "averageSpeed": 2.3320000171661377, "averageMovingSpeed": 2.374782013747454, "maxSpeed": 2.6029999256134033, "calories": 522.0, "bmrCalories": 58.0, "averageHR": 158.0, "maxHR": 171.0, "averageRunCadence": 151.65625, "maxRunCadence": 173.0, "strideLength": 92.28567417513023, "trainingEffect": 4.599999904632568, "anaerobicTrainingEffect": 0.0, "aerobicTrainingEffectMessage": "HIGHLY_IMPROVING_LACTATE_THRESHOLD_13", "anaerobicTrainingEffectMessage": "NO_ANAEROBIC_BENEFIT_0", "waterEstimated": 249.0, "minActivityLapDuration": 443.458, "moderateIntensityMinutes": 0, "vigorousIntensityMinutes": 40, "steps": 6342}, "splitSummaries": [{"distance": 3.94, "duration": 10.002, "averageSpeed": 0.39399999380111694, "maxSpeed": 1.5210000276565552, "calories": 0.0, "bmrCalories": 0.0, "averageHR": 112.0, "maxHR": 112.0, "averageRunCadence": 127.0, "maxRunCadence": 155.0, "strideLength": 18.61045167811802, "totalExerciseReps": 0, "splitType": "RWD_WALK", "noOfSplits": 1, "maxDistance": 3}, {"distance": 5817.49, "duration": 2471.999, "movingDuration": 2430.0, "averageSpeed": 2.3529999256134033, "averageMovingSpeed": 2.394561204213131, "maxSpeed": 2.6029999256134033, "calories": 520.0, "bmrCalories": 60.0, "averageHR": 159.0, "maxHR": 171.0, "averageRunCadence": 152.78125, "maxRunCadence": 173.0, "strideLength": 92.40796448757278, "totalExerciseReps": 0, "splitType": "RWD_RUN", "noOfSplits": 3, "maxDistance": 2794}, {"distance": 0.0, "duration": 17.651, "movingDuration": 0.0, "averageSpeed": 0.0, "maxSpeed": 0.0, "calories": 4.0, "bmrCalories": 0.0, "averageHR": 162.0, "maxHR": 166.0, "averageRunCadence": 30.0, "maxRunCadence": 150.0, "strideLength": 0.0, "totalExerciseReps": 0, "splitType": "RWD_STAND", "noOfSplits": 3, "maxDistance": 0}]}