{"activityId": 16559997429, "activityName": "Strength", "startTimeLocal": "2024-07-23 07:59:30", "startTimeGMT": "2024-07-23 12:59:30", "activityType": {"typeId": 13, "typeKey": "strength_training", "parentTypeId": 29, "isHidden": false, "trimmable": false, "restricted": false}, "eventType": {"typeId": 9, "typeKey": "uncategorized", "sortOrder": 10}, "distance": 0.0, "duration": 2551.43310546875, "elapsedDuration": 2551.43310546875, "movingDuration": 676.22998046875, "averageSpeed": 0.0, "hasPolyline": false, "hasImages": false, "ownerId": 104355181, "ownerDisplayName": "4f38881e-d967-46da-bb7b-6d423fe5470d", "ownerFullName": "Dhinesh", "ownerProfileImageUrlSmall": "https://s3.amazonaws.com/garmin-connect-prod/profile_images/13af3aa6-824b-4db4-8d04-74c652855cde-104355181.png", "ownerProfileImageUrlMedium": "https://s3.amazonaws.com/garmin-connect-prod/profile_images/1b9a9653-c6bb-42f9-8b18-5aa78975da3a-104355181.png", "ownerProfileImageUrlLarge": "https://s3.amazonaws.com/garmin-connect-prod/profile_images/fe3cf31e-c58e-4bd8-83f8-42b825174ca3-104355181.png", "calories": 264.0, "bmrCalories": 62.0, "averageHR": 117.0, "maxHR": 148.0, "steps": 274, "userRoles": ["SCOPE_GOLF_API_READ", "SCOPE_ATP_READ", "SCOPE_DIVE_API_WRITE", "SCOPE_COMMUNITY_COURSE_ADMIN_READ", "SCOPE_DIVE_API_READ", "SCOPE_DI_OAUTH_2_CLIENT_READ", "SCOPE_CONNECT_WRITE", "SCOPE_COMMUNITY_COURSE_WRITE", "SCOPE_MESSAGE_GENERATION_READ", "SCOPE_DI_OAUTH_2_CLIENT_REVOCATION_ADMIN", "SCOPE_CONNECT_WEB_TEMPLATE_RENDER", "SCOPE_OMT_SUBSCRIPTION_ADMIN_READ", "SCOPE_CONNECT_NON_SOCIAL_SHARED_READ", "SCOPE_CONNECT_READ", "SCOPE_DI_OAUTH_2_TOKEN_ADMIN", "ROLE_CONNECTUSER", "ROLE_FITNESS_USER", "ROLE_WELLNESS_USER", "ROLE_OUTDOOR_USER", "ROLE_GHS_USER"], "privacy": {"typeId": 2, "typeKey": "private"}, "userPro": false, "hasVideo": false, "timeZoneId": 152, "beginTimestamp": 1721739570000, "sportTypeId": 10, "aerobicTrainingEffect": 2.299999952316284, "anaerobicTrainingEffect": 1.2000000476837158, "deviceId": 3470809531, "minTemperature": 30.0, "maxTemperature": 33.0, "summarizedExerciseSets": [{"category": "BENCH_PRESS", "reps": 16, "volume": 544000, "duration": 82298.00033569336, "sets": 2}, {"category": "CURL", "reps": 45, "volume": 710423, "duration": 159375.9994506836, "sets": 5}, {"category": "TRICEPS_EXTENSION", "reps": 8, "volume": 54496, "duration": 45456.00128173828, "sets": 1}, {"category": "PULL_UP", "reps": 16, "volume": 0, "duration": 83935.99891662598, "sets": 3}, {"category": "UNKNOWN", "reps": 32, "volume": 272000, "duration": 220705.9998512268, "sets": 5}, {"category": "ROW", "reps": 20, "volume": 136240, "duration": 84458.00018310547, "sets": 2}], "summarizedDiveInfo": {"summarizedDiveGases": []}, "manufacturer": "GARMIN", "lapCount": 1, "waterEstimated": 578.0, "totalSets": 18, "activeSets": 18, "totalReps": 137, "trainingEffectLabel": "ANAEROBIC_CAPACITY", "activityTrainingLoad": 33.3951416015625, "minActivityLapDuration": 2551.43310546875, "aerobicTrainingEffectMessage": "MAINTAINING_AEROBIC_FITNESS_1", "anaerobicTrainingEffectMessage": "MINOR_ANAEROBIC_BENEFIT_15", "splitSummaries": [], "hasSplits": false, "moderateIntensityMinutes": 35, "vigorousIntensityMinutes": 3, "differenceBodyBattery": -11, "purposeful": false, "manualActivity": false, "pr": false, "autoCalcCalories": false, "elevationCorrected": false, "atpActivity": false, "favorite": false, "decoDive": false, "parent": false}