{"activityId": 14312106978, "activityUUID": {"uuid": "791053f2-87a8-4f81-999b-957044eb4865"}, "activityName": "Pflugerville Future", "userProfileId": 104355181, "isMultiSportParent": false, "activityTypeDTO": {"typeId": 4, "typeKey": "other", "parentTypeId": 17, "isHidden": false, "restricted": false, "trimmable": true}, "eventTypeDTO": {"typeId": 9, "typeKey": "uncategorized", "sortOrder": 10}, "accessControlRuleDTO": {"typeId": 2, "typeKey": "private"}, "timeZoneUnitDTO": {"unitId": 152, "unitKey": "America/Chicago", "factor": 0.0, "timeZone": "America/Chicago"}, "metadataDTO": {"isOriginal": true, "deviceApplicationInstallationId": 966701, "agentApplicationInstallationId": null, "agentString": null, "fileFormat": {"formatId": 7, "formatKey": "fit"}, "associatedCourseId": null, "lastUpdateDate": "2024-03-08T16:03:47.0", "uploadedDate": "2024-03-08T16:03:47.0", "videoUrl": null, "hasPolyline": false, "hasChartData": true, "hasHrTimeInZones": true, "hasPowerTimeInZones": false, "userInfoDto": {"userProfilePk": 104355181, "displayname": "4f38881e-d967-46da-bb7b-6d423fe5470d", "fullname": "Dhinesh", "profileImageUrlLarge": "https://s3.amazonaws.com/garmin-connect-prod/profile_images/fe3cf31e-c58e-4bd8-83f8-42b825174ca3-104355181.png", "profileImageUrlMedium": "https://s3.amazonaws.com/garmin-connect-prod/profile_images/1b9a9653-c6bb-42f9-8b18-5aa78975da3a-104355181.png", "profileImageUrlSmall": "https://s3.amazonaws.com/garmin-connect-prod/profile_images/13af3aa6-824b-4db4-8d04-74c652855cde-104355181.png", "userPro": false}, "childIds": [], "childActivityTypes": [], "sensors": null, "activityImages": [], "manufacturer": "GARMIN", "diveNumber": null, "lapCount": 1, "associatedWorkoutId": null, "isAtpActivity": null, "deviceMetaDataDTO": {"deviceId": "3383025111", "deviceTypePk": 35576, "deviceVersionPk": 966701}, "hasIntensityIntervals": false, "hasSplits": false, "eBikeMaxAssistModes": null, "eBikeBatteryUsage": null, "eBikeBatteryRemaining": null, "eBikeAssistModeInfoDTOList": null, "hasRunPowerWindData": null, "calendarEventInfo": null, "groupRideUUID": null, "hasHeatMap": false, "gcj02": false, "runPowerWindDataEnabled": null, "personalRecord": false, "elevationCorrected": false, "trimmed": false, "manualActivity": false, "autoCalcCalories": false, "favorite": false}, "summaryDTO": {"startTimeLocal": "2024-03-08T09:06:27.0", "startTimeGMT": "2024-03-08T15:06:27.0", "startLatitude": 30.444136653095484, "startLongitude": -97.56267347373068, "distance": 1.65, "duration": 3283.822, "movingDuration": 3.0, "elapsedDuration": 3283.822, "elevationGain": 0.0, "elevationLoss": 0.0, "maxElevation": 190.0, "minElevation": 190.0, "averageSpeed": 0.0010000000474974513, "averageMovingSpeed": 0.549999992052714, "maxSpeed": 1.3530000448226926, "calories": 469.0, "bmrCalories": 80.0, "averageHR": 136.0, "maxHR": 172.0, "trainingEffect": 4.0, "anaerobicTrainingEffect": 2.299999952316284, "aerobicTrainingEffectMessage": "HIGHLY_IMPROVING_AEROBIC_ENDURANCE_10", "anaerobicTrainingEffectMessage": "MAINTAINING_ANAEROBIC_BASE_1", "endLatitude": 30.444162720814347, "endLongitude": -97.56266819313169, "maxVerticalSpeed": 0.0, "waterEstimated": 328.0, "minActivityLapDuration": 3283.822, "moderateIntensityMinutes": 31, "vigorousIntensityMinutes": 23, "steps": 1186}, "locationName": "Pflugerville"}