{"dailySleepDTO": {"id": 1704691260000, "userProfilePK": 104355181, "calendarDate": "2024-01-08", "sleepTimeSeconds": 27600, "napTimeSeconds": 0, "sleepWindowConfirmed": true, "sleepWindowConfirmationType": "enhanced_confirmed_final", "sleepStartTimestampGMT": 1704691260000, "sleepEndTimestampGMT": 1704719040000, "sleepStartTimestampLocal": 1704669660000, "sleepEndTimestampLocal": 1704697440000, "autoSleepStartTimestampGMT": 1704691020000, "autoSleepEndTimestampGMT": 1704718860000, "sleepQualityTypePK": null, "sleepResultTypePK": null, "unmeasurableSleepSeconds": 0, "deepSleepSeconds": 2940, "lightSleepSeconds": 18360, "remSleepSeconds": 6300, "awakeSleepSeconds": 180, "deviceRemCapable": true, "retro": false, "averageRespirationValue": 15.0, "lowestRespirationValue": 11.0, "highestRespirationValue": 26.0}, "sleepMovement": null, "remSleepData": true, "sleepLevels": null, "skinTempDataExists": false, "bodyBatteryChange": 42, "restingHeartRate": 63}